vdct/__init__.py
vdct/_modidx.py
vdct/atyp.py
vdct/cast.py
vdct/core.py
vdct/flag.py
vdct/util.py
vdct-0.0.1.dist-info/LICENSE
vdct-0.0.1.dist-info/METADATA
vdct-0.0.1.dist-info/WHEEL
vdct-0.0.1.dist-info/entry_points.txt
vdct-0.0.1.dist-info/top_level.txt
vdct-0.0.1.dist-info/RECORD
